callable_cli/__init__.py
callable_cli/version.py
tests/__init__.py
tests/test_callable_cli.py
callable_cli-0.0.1.dist-info/METADATA
callable_cli-0.0.1.dist-info/WHEEL
callable_cli-0.0.1.dist-info/top_level.txt
callable_cli-0.0.1.dist-info/RECORD
