Metadata-Version: 2.1
Name: callable-cli
Version: 0.0.1
Summary: A wrapper for building click CLIs that retains callable functions
Home-page: https://github.com/chrispyles/callable-cli
Author: Chris Pyles
License: BSD-3-Clause
Platform: UNKNOWN
Classifier: Programming Language :: Python :: 3
Classifier: License :: OSI Approved :: BSD License
Classifier: Operating System :: OS Independent
Requires-Dist: click
